mugennocore/model/chapter.py
mugennocore/model/genre.py
mugennocore/model/interfaces.py
mugennocore/model/manga.py
mugennocore/model/page.py
mugennocore-0.2.0.dist-info/METADATA
mugennocore-0.2.0.dist-info/WHEEL
mugennocore-0.2.0.dist-info/RECORD
