Metadata-Version: 2.3
Name: mugennocore
Version: 0.2.0
Summary: Shared lib for the mugen project. Components used by two or more of the mugen ecossystem.
License: GPLv3
Author: Kyamel
Author-email: lcamelo200@gmail.com
Requires-Python: >=3.12
Classifier: License :: Other/Proprietary License
Classifier: Programming Language :: Python :: 3
Classifier: Programming Language :: Python :: 3.12
Classifier: Programming Language :: Python :: 3.13
